[
    {
        "name" : "Game 1",
        "desc" : "Pixel Action Game",
        "category" : "Action",
        "img" : "assets/img/PIXEL BG.jpg"
    },
    {
        "name" : "Game 2",
        "desc" : "An Action Game",
        "category" : "Action",
        "img" : "assets/img/action.jpg"
    },
    {
        "name" : "Game 3",
        "desc" : "FPG Game",
        "category" : "FPG",
        "img" : "assets/img/FPS.jpg"
    },
    {
        "name" : "Game 4",
        "desc" : "Fighting Game",
        "category" : "Fighting Game",
        "img" : "assets/img/fighting.jpg"
    }
]